NEMO_contracts/__init__.py
NEMO_contracts/admin.py
NEMO_contracts/apps.py
NEMO_contracts/customization.py
NEMO_contracts/models.py
NEMO_contracts/urls.py
NEMO_contracts/management/__init__.py
NEMO_contracts/management/commands/__init__.py
NEMO_contracts/management/commands/send_email_contract_reminders.py
NEMO_contracts/migrations/0001_initial.py
NEMO_contracts/migrations/0002_increase_document_path_length.py
NEMO_contracts/migrations/0003_documents_display_order.py
NEMO_contracts/migrations/0004_default_display_order.py
NEMO_contracts/migrations/0005_alter_contractoragreementdocuments_name_and_more.py
NEMO_contracts/migrations/0006_alter_contractoragreementdocuments_display_order_and_more.py
NEMO_contracts/migrations/__init__.py
NEMO_contracts/templates/contracts/contractors.html
NEMO_contracts/templates/contracts/contracts_and_procurements.html
NEMO_contracts/templates/contracts/procurements.html
NEMO_contracts/templates/contracts/service_contracts.html
NEMO_contracts/templates/customizations/customizations_contracts.html
NEMO_contracts/tests/__init__.py
NEMO_contracts/tests/test_contracts.py
NEMO_contracts/tests/test_settings.py
NEMO_contracts/views/__init__.py
NEMO_contracts/views/contracts.py
NEMO_contracts-1.0.1.dist-info/LICENSE
NEMO_contracts-1.0.1.dist-info/METADATA
NEMO_contracts-1.0.1.dist-info/WHEEL
NEMO_contracts-1.0.1.dist-info/top_level.txt
NEMO_contracts-1.0.1.dist-info/RECORD
