Metadata-Version: 2.2
Name: NEMO-contracts
Version: 1.0.1
Summary: Plugin for NEMO allowing facility managers to keep track of service contracts, procurement and contractors
Author-email: Center for Nanoscale Science and Technology <CNSTapplications@nist.gov>
License: # NIST Software Licensing Statement
Project-URL: Homepage, https://github.com/usnistgov/NEMO-contracts
Project-URL: Changelog, https://github.com/usnistgov/NEMO-contracts/releases
Project-URL: Issues, https://github.com/usnistgov/NEMO-contracts/issues
Keywords: NEMO
Classifier: Development Status :: 5 - Production/Stable
Classifier: Environment :: Web Environment
Classifier: Intended Audience :: Science/Research
Classifier: Intended Audience :: System Administrators
Classifier: License :: Public Domain
Classifier: Natural Language :: English
Classifier: Operating System :: OS Independent
Classifier: Framework :: Django :: 4.2
Classifier: Programming Language :: Python :: 3.9
Classifier: Programming Language :: Python :: 3.10
Classifier: Programming Language :: Python :: 3.11
Classifier: Programming Language :: Python :: 3.12
Classifier: Programming Language :: Python :: 3.13
Requires-Python: >=3.9
License-File: LICENSE
Requires-Dist: django
Provides-Extra: nemo-ce
Requires-Dist: NEMO-CE>=7.0.0; extra == "nemo-ce"
Provides-Extra: nemo
Requires-Dist: NEMO>=7.0.0; extra == "nemo"
Provides-Extra: dev-tools
Requires-Dist: pre-commit; extra == "dev-tools"
Requires-Dist: djlint; extra == "dev-tools"
Requires-Dist: black; extra == "dev-tools"
